{
  "0e93b819cc2e8121f7281dc8e4eaaf78" : {
    "statistic" : {
      "failed" : 0,
      "broken" : 0,
      "skipped" : 0,
      "passed" : 1,
      "unknown" : 0,
      "total" : 1
    },
    "items" : [ {
      "uid" : "710d20f57b3ebe8b",
      "reportUrl" : "https://robert19940123.github.io/selenium-py-peldatar/34//#testresult/710d20f57b3ebe8b",
      "status" : "passed",
      "time" : {
        "start" : 1624969128229,
        "stop" : 1624969128229,
        "duration" : 0
      }
    } ]
  },
  "753cdf21aa3257d3e2249d83346a13e6" : {
    "statistic" : {
      "failed" : 0,
      "broken" : 0,
      "skipped" : 0,
      "passed" : 1,
      "unknown" : 0,
      "total" : 1
    },
    "items" : [ {
      "uid" : "5d75ab38e9067105",
      "reportUrl" : "https://robert19940123.github.io/selenium-py-peldatar/34//#testresult/5d75ab38e9067105",
      "status" : "passed",
      "time" : {
        "start" : 1624969128227,
        "stop" : 1624969128228,
        "duration" : 1
      }
    } ]
  },
  "77caee529814bb5616db6b28df37c87c" : {
    "statistic" : {
      "failed" : 0,
      "broken" : 0,
      "skipped" : 0,
      "passed" : 1,
      "unknown" : 0,
      "total" : 1
    },
    "items" : [ {
      "uid" : "fd4bf50ea50143e9",
      "reportUrl" : "https://robert19940123.github.io/selenium-py-peldatar/34//#testresult/fd4bf50ea50143e9",
      "status" : "passed",
      "time" : {
        "start" : 1624969128226,
        "stop" : 1624969128226,
        "duration" : 0
      }
    } ]
  },
  "0cc1fa42e1c19a0d3fd610d45c4ba65a" : {
    "statistic" : {
      "failed" : 0,
      "broken" : 0,
      "skipped" : 0,
      "passed" : 1,
      "unknown" : 0,
      "total" : 1
    },
    "items" : [ {
      "uid" : "47fe17544e69ed7f",
      "reportUrl" : "https://robert19940123.github.io/selenium-py-peldatar/34//#testresult/47fe17544e69ed7f",
      "status" : "passed",
      "time" : {
        "start" : 1624969128216,
        "stop" : 1624969128217,
        "duration" : 1
      }
    } ]
  }
}